pixiv/__init__.py
pixiv/exceptions.py
pixiv/pixiv.py
pixiv/utils.py
pixiv-0.1.1.dist-info/top_level.txt
pixiv-0.1.1.dist-info/METADATA
pixiv-0.1.1.dist-info/DESCRIPTION.rst
pixiv-0.1.1.dist-info/metadata.json
pixiv-0.1.1.dist-info/WHEEL
pixiv-0.1.1.dist-info/RECORD
