Metadata-Version: 2.0
Name: pixiv
Version: 0.1.1
Summary: Pixiv API client.
Home-page: https://pixiv.readthedocs.org
Author: Louis Taylor
Author-email: louis@kragniz.eu
License: LGPLv3
Keywords: pixiv
Platform: UNKNOWN
Classifier: Development Status :: 2 - Pre-Alpha
Classifier: Intended Audience :: Developers
Classifier: License :: OSI Approved :: GNU Lesser General Public License v3 (LGPLv3)
Classifier: Natural Language :: English
Classifier: Programming Language :: Python :: 2
Classifier: Programming Language :: Python :: 2.7
Classifier: Programming Language :: Python :: 3
Classifier: Programming Language :: Python :: 3.4
Classifier: Programming Language :: Python :: 3.5
Requires-Dist: requests
Requires-Dist: six
